{
	"sharing_edit_help_tasklist": "La funcionalidad \"Compartición\" permite de compartir las listas de tareas con otros usuarios.",
	"sharing_edit_help_tasklist_dot_0": "Insertar la dirección email de la persona con la cual desea compartir la lista de tareas.",
	"sharing_edit_help_tasklist_dot_2": "Para cada usuario insertado serán atribuidos de manera automática los permisos de acceso en lectura a la lista de tareas.",
	"sharing_edit_help_tasklist_dot_3": "Será posible añadir ulteriores permisos seleccionando las opciones apropiadas:",
	"sharing_edit_help_tasklist_dot_3_1": "Modificación: permite la modificación de tareas que existen en la lista de tareas",
	"sharing_edit_help_tasklist_dot_3_2": "Creación: permite la creación de nuevas tareas en la lista de tareas",
	"sharing_edit_help_tasklist_dot_3_3": "Cancelación: permite la eliminación de tareas que se encuentran en la lista de tareas",
	"task_back_to_category": "Volver a",
	"task_display_deleted": "La tarea ha sido eliminada",
	"task_display_saved": "La tarea ha sido guardada",
	"task_end_on": "Terminar a las",
	"task_end_on_column": "Terminar a las",
	"task_lists": "Listas",
	"task_mark_done": "Marcar como Hecho",
	"task_name": "Título",
	"task_name_personal": "Personal",
	"task_note": "Notas",
	"task_percent": "% Completo",
	"task_priority": "Prioridad",
	"task_priority_column": "prioridad",
	"task_save_into": "en",
	"task_save_task": "Guardar tarea",
	"task_start_on": "Iniciar a las",
	"task_start_on_column": "Iniciar a las",
	"task_status": "Estado",
	"task_status_all": "Todos",
	"task_status_column": "Estado",
	"task_status_done": "Hecho",
	"task_status_inprogress": "En progreso",
	"task_status_open": "No realizado",
	"task_status_postponed": "Aplazado",
	"task_status_tobedone": "Pendiente",
	"task_status_waiting": "La espera de otra persona",
	"task_task": "Tarea",
	"task_title_column": "Título",
	"tasklist": "Listas de tareas",
	"tasklist_cancel": "Cancelar",
	"tasklist_create": "Crear",
	"tasklist_create_title": "Nueva lista de tareas",
	"tasklist_delete": "Cancela",
	"tasklist_delete_confirm": "¡La lista de tareas será eliminada de manera definitiva!",
	"tasklist_edit_title": "Modifica",
	"tasklist_items_will_be_definitively_deleted": "Las tareas seleccionadas serán eliminadas de manera definitiva!",
	"tasklist_items_selected": "Seleccionadas:",
	"tasklist_modified": "Lista de tareas actualizada correctamente",
	"tasklist_no_tasks": "Sin tareas",
	"tasklist_properties": "Propiedades",
	"tasklist_ok": "Ok",
	"tasklist_set_comment": "Descripción",
	"tasklist_set_name": "Nombre",
	"tasklist_setname": "Nombre lista de tareas",
	"tasklist_share_title": "Compartir esta lista de tareas",
	"tasklist_shared_address_book": "Listas externas",
	"tasklist_system_name": "Personal",
	"tasklist_update": "Actualizar"
}
